<annotation>
	<folder>train</folder>
	<filename>P_20181127_124558.jpg</filename>
	<path>/home/alexandre/Documents/MonPetitRecycleur/models-master/research/object_detection/Custom/dataset-resized/orga_vs_trash vs cutlery/train/P_20181127_124558.jpg</path>
	<source>
		<database>Unknown</database>
	</source>
	<size>
		<width>819</width>
		<height>460</height>
		<depth>3</depth>
	</size>
	<segmented>0</segmented>
	<object>
		<name>trash</name>
		<pose>Unspecified</pose>
		<truncated>0</truncated>
		<difficult>0</difficult>
		<bndbox>
			<xmin>260</xmin>
			<ymin>148</ymin>
			<xmax>379</xmax>
			<ymax>264</ymax>
		</bndbox>
	</object>
	<object>
		<name>cutlery</name>
		<pose>Unspecified</pose>
		<truncated>1</truncated>
		<difficult>0</difficult>
		<bndbox>
			<xmin>565</xmin>
			<ymin>1</ymin>
			<xmax>641</xmax>
			<ymax>305</ymax>
		</bndbox>
	</object>
	<object>
		<name>cutlery</name>
		<pose>Unspecified</pose>
		<truncated>0</truncated>
		<difficult>0</difficult>
		<bndbox>
			<xmin>152</xmin>
			<ymin>48</ymin>
			<xmax>219</xmax>
			<ymax>239</ymax>
		</bndbox>
	</object>
	<object>
		<name>cup</name>
		<pose>Unspecified</pose>
		<truncated>1</truncated>
		<difficult>0</difficult>
		<bndbox>
			<xmin>272</xmin>
			<ymin>326</ymin>
			<xmax>413</xmax>
			<ymax>460</ymax>
		</bndbox>
	</object>
</annotation>
